XXQG/__init__.py
XXQG/config.py
XXQG/models/__init__.py
XXQG/models/log.py
XXQG/models/user.py
XXQG/resource/LICENSE
XXQG/resource/dist/assets/icon.jpg
XXQG/resource/dist/assets/icon128.png
XXQG/resource/dist/assets/icon128_gray.png
XXQG/resource/dist/assets/icon16.png
XXQG/resource/dist/assets/icon16_gray.png
XXQG/resource/dist/assets/icon32.png
XXQG/resource/dist/assets/icon32_gray.png
XXQG/resource/dist/assets/icon48.png
XXQG/resource/dist/assets/icon48_gray.png
XXQG/resource/dist/assets/icon_gray.jpg
XXQG/resource/dist/background/index.js
XXQG/resource/dist/inject/exam/index.js
XXQG/resource/dist/inject/home/index.js
XXQG/resource/dist/inject/readAndWatch/index.js
XXQG/resource/dist/popup/icon.jpg
XXQG/resource/dist/popup/index.css
XXQG/resource/dist/popup/index.html
XXQG/resource/dist/popup/index.js
XXQG/resource/manifest.json
XXQG/schemas/__init__.py
XXQG/schemas/common.py
XXQG/utils/__init__.py
XXQG/utils/activity.py
XXQG/utils/handle.py
XXQG/utils/login.py
XXQG/utils/path.py
XXQG/utils/rule.py
xxqg-0.0.2.dist-info/LICENSE
xxqg-0.0.2.dist-info/METADATA
xxqg-0.0.2.dist-info/WHEEL
xxqg-0.0.2.dist-info/RECORD
