Metadata-Version: 2.1
Name: XXQG
Version: 0.0.2
Summary: 基于nonebot2的学习强国挂机插件，可每日自动学习，29分/天
Home-page: https://github.com/YouthLearning/XXQG
License: MIT
Author: TeenStudyFlow
Author-email: TeenStudyFlow@gmail.com
Requires-Python: >=3.8,<4.0
Classifier: License :: OSI Approved :: MIT License
Classifier: Programming Language :: Python :: 3
Classifier: Programming Language :: Python :: 3.8
Classifier: Programming Language :: Python :: 3.9
Classifier: Programming Language :: Python :: 3.10
Classifier: Programming Language :: Python :: 3.11
Classifier: Programming Language :: Python :: 3.12
Requires-Dist: httpx (>=0.27.0,<0.28.0)
Requires-Dist: nonebot-adapter-onebot (>=2.4.4,<3.0.0)
Requires-Dist: nonebot-plugin-apscheduler (>=0.5.0,<0.6.0)
Requires-Dist: nonebot2 (>=2.0.0,<3.0.0)
Requires-Dist: playwright (>=1.45.0,<2.0.0)
Requires-Dist: tortoise-orm (>=0.19.3,<0.20.0)
